setup.cfg
setup.py
profilegrab/__init__.py
profilegrab/grab.py
profilegrab/scrapers.py
profilegrab/settings.py
profilegrab/utils.py
profilegrab.egg-info/PKG-INFO
profilegrab.egg-info/SOURCES.txt
profilegrab.egg-info/dependency_links.txt
profilegrab.egg-info/requires.txt
profilegrab.egg-info/top_level.txt