Metadata-Version: 1.1
Name: profilegrab
Version: 0.1.3
Summary: Very simple social media scraping for Python.
Home-page: https://github.com/hack-c/profilegrab
Author: Charlie Hack
Author-email: charlie@205consulting.com
License: UNKNOWN
Download-URL: https://github.com/hack-c/profilegrab/tarball/0.1
Platform: UNKNOWN
